LICENSE
MANIFEST.in
README.md
setup.cfg
setup.py
biastools/__init__.py
biastools/biastools.py
biastools/biastools_align.py
biastools/biastools_align.sh
biastools/biastools_analysis.sh
biastools/biastools_compare.sh
biastools/biastools_predict.sh
biastools/biastools_scan.py
biastools/biastools_simulation.sh
biastools/compare_bias_with_RD.py
biastools/consensus_vcf_map_adaptive.py
biastools/filter_het_VCF.py
biastools/golden_graph.py
biastools/golden_graph_report.py
biastools/indel_balance_extract.plot.py
biastools/indel_balance_extract.py
biastools/indel_balance_plot.len.py
biastools/indel_balance_plot.py
biastools/merge_baseline.py
biastools/predict_experiment.py
biastools/predict_model.py
biastools/ref_bi_context.eff_len.py
biastools/ref_bi_context.mop.py
biastools/ref_bi_context.py
biastools/ref_bi_context.v2.py
biastools/ref_bi_context.v3.py
biastools/ref_bi_context_v3.py
biastools/ref_bi_modify.py
biastools/ref_bi_multiprocess.py
biastools/ref_bi_naive.py
biastools/ref_bi_refact.backup.py
biastools/sample_baseline.py
biastools/scanning_bias.py
biastools/vcf_to_bed.py
biastools.egg-info/PKG-INFO
biastools.egg-info/SOURCES.txt
biastools.egg-info/dependency_links.txt
biastools.egg-info/entry_points.txt
biastools.egg-info/not-zip-safe
biastools.egg-info/requires.txt
biastools.egg-info/top_level.txt